Workbook
Name aporte: APP!$D$13
Name patrimonio: APP!$D$16
Name qtd_anos: APP!$D$14
Name rendimento_carteira: APP!$D$9
Name salario: APP!$D$8
Name taxa_mensal: APP!$D$15

Sheet APP
B7: CONFIGURAÇÕES
B8: Salário | D8: 2500
B9: Rendimento de Carteira | D9: 0.01
B10: Sugestão de Investimento | D10: =$D$8*30% -> 750
B12: INVESTIMENTO MENSAL
B13: Quanto invesstir por mês? | D13: 500
B14: Por quantos anos? | D14: 5
B15: Taxa de rendimento mensal? | D15: 0.0108
B16: Patrimônio acumulado? | D16: =FV(taxa_mensal,qtd_anos*12,-aporte) -> 41902.01
B17: Dividendos mensais? | D17: =patrimonio*taxa_mensal -> 452.5417
B19: CENÁRIO | D19: Dividendos
A20: 2 | B20: Quanto em 2 anos? | C20: =FV($D$15,$A20*12,-$D$13) -> 13615.432 | D20: =C20*rendimento_carteira -> 136.15432
A21: 5 | B21: Quanto em 5 anos? | C21: =FV($D$15,$A21*12,-$D$13) -> 41902.01 | D21: =C21*rendimento_carteira -> 419.0201
A22: 10 | B22: Quanto em 10 anos? | C22: =FV($D$15,$A22*12,-$D$13) -> 121728.83 | D22: =C22*rendimento_carteira -> 1217.2883
A23: 20 | B23: Quanto em 20 anos? | C23: =FV($D$15,$A23*12,-$D$13) -> 563524.5 | D23: =C23*rendimento_carteira -> 5635.245
A24: 30 | B24: Quanto em 30 anos? | C24: =FV($D$15,$A24*12,-$D$13) -> 2166952.4 | D24: =C24*rendimento_carteira -> 21669.524
B26: PERFIL | C26: Agressivo
B27: VALOR A SER INVESTIDO POR MÊS | C27: =aporte -> 500
B29: TIPO DE FII | C29: Percentual Sugerido | D29: Valores
B30: PAPEL | C30: =VLOOKUP($B30&"-"&$C$26,Apoio!B2:D22,3,FALSE) -> 0.5 | D30: =aporte*$C30 -> 250
B31: TIJOLO | C31: =VLOOKUP($B31&"-"&$C$26,Apoio!B3:D23,3,FALSE) -> 0.1 | D31: =aporte*$C31 -> 50
B32: HÍBRIDOS | C32: =VLOOKUP($B32&"-"&$C$26,Apoio!B4:D24,3,FALSE) -> 0.05 | D32: =aporte*$C32 -> 25
B33: FOFs | C33: =VLOOKUP($B33&"-"&$C$26,Apoio!B5:D25,3,FALSE) -> 0.05 | D33: =aporte*$C33 -> 25
B34: DESENVOLVIMENTO | C34: =VLOOKUP($B34&"-"&$C$26,Apoio!B6:D26,3,FALSE) -> 0.2 | D34: =aporte*$C34 -> 100
B35: HOTELARIAS | C35: =VLOOKUP($B35&"-"&$C$26,Apoio!B7:D27,3,FALSE) -> 0.1 | D35: =aporte*$C35 -> 50
D36: =SUM($D$30:$D$35) -> 500

Sheet Apoio
B2: Chave | C2: TIPO DE FII | D2: Conservador
B3: =$C3&"-"&$D$2 -> PAPEL-Conservador | C3: PAPEL | D3: 0.3
B4: =$C4&"-"&$D$2 -> TIJOLO-Conservador | C4: TIJOLO | D4: 0.5
B5: =$C5&"-"&$D$2 -> HÍBRIDOS-Conservador | C5: HÍBRIDOS | D5: 0.1
B6: =$C6&"-"&$D$2 -> FOFs-Conservador | C6: FOFs | D6: 0.1
B7: =$C7&"-"&$D$2 -> DESENVOLVIMENTO-Conservador | C7: DESENVOLVIMENTO | D7: 0
B8: =$C8&"-"&$D$2 -> HOTELARIAS-Conservador | C8: HOTELARIAS | D8: 0
B9: Chave | C9: TIPO DE FII | D9: Moderado
B10: =$C10&"-"&$D$9 -> PAPEL-Moderado | C10: PAPEL | D10: 0.32
B11: =$C11&"-"&$D$9 -> TIJOLO-Moderado | C11: TIJOLO | D11: 0.35
B12: =$C12&"-"&$D$9 -> HÍBRIDOS-Moderado | C12: HÍBRIDOS | D12: 0.08
B13: =$C13&"-"&$D$9 -> FOFs-Moderado | C13: FOFs | D13: 0.05
B14: =$C14&"-"&$D$9 -> DESENVOLVIMENTO-Moderado | C14: DESENVOLVIMENTO | D14: 0.1
B15: =$C15&"-"&$D$9 -> HOTELARIAS-Moderado | C15: HOTELARIAS | D15: 0.1
B16: Chave | C16: TIPO DE FII | D16: Agressivo
B17: =$C17&"-"&$D$16 -> PAPEL-Agressivo | C17: PAPEL | D17: 0.5
B18: =$C18&"-"&$D$16 -> TIJOLO-Agressivo | C18: TIJOLO | D18: 0.1
B19: =$C19&"-"&$D$16 -> HÍBRIDOS-Agressivo | C19: HÍBRIDOS | D19: 0.05
B20: =$C20&"-"&$D$16 -> FOFs-Agressivo | C20: FOFs | D20: 0.05
B21: =$C21&"-"&$D$16 -> DESENVOLVIMENTO-Agressivo | C21: DESENVOLVIMENTO | D21: 0.2
B22: =$C22&"-"&$D$16 -> HOTELARIAS-Agressivo | C22: HOTELARIAS | D22: 0.1
